{
	"builders": [
	{
		"name": "Windows2012x64",
		"output_directory": "Windows2012x64",
		"type": "vmware-iso",
		"headless": false,
		"vm_name": "Windows2012x64",
		"vmdk_name": "Windows2012x64",
		"iso_url": "ISO/en_windows_server_2012_x64_dvd_915478.iso",
		"iso_checksum": "da91135483e24689bfdaf05d40301506",
		"iso_checksum_type": "md5",
		"communicator": "winrm",
		"winrm_username": "administrator",
		"winrm_password": "P@ssw0rd01",
		"winrm_timeout": "4h",
		"shutdown_command": "shutdown -s -f -t 1",
		"shutdown_timeout": "5m",
		"guest_os_type": "windows8srv-64",
		"disk_type_id": "0",
		"disk_size": "1000000",
		"Version": "12",
		"floppy_files": [
			"scripts/Build.ps1",
			"scripts/build01-vmware.ps1",
			"scripts/build02-caffeine.ps1",
			"scripts/build03-misc.cmd",
			"scripts/build04-Enablewinrm.ps1",
			"FloppyFiles/Windows2012x64/autounattend.xml"
		]
	}
	]
}
